archive/profiling/debug_PSF.py
archive/profiling/debug_deconv.py
archive/profiling/profile_PSF.py
archive/profiling/profile_deconv.py
archive/profiling/read_debug.py
docs/conf.py
scripts/1_generate_psf.py
scripts/2_deconvolve.py
scripts/test_PSF_generator/check_utils.py
scripts/test_PSF_generator/PSF/WFI-time-series-2M1134/get_lesta_WFIpsf.py
scripts/test_PSF_generator/archive/check_astrometry_photometry.py
scripts/test_PSF_generator/archive/check_psf_fidelity.py
scripts/test_PSF_generator/archive/compare_PSF.py
scripts/test_PSF_generator/archive/run_psf_reconstruction.py
scripts/test_PSF_generator/archive/run_psfr.py
scripts/test_PSF_generator/archive/test_generator.py
scripts/test_deconvolution/utils_psf.py
scripts/test_deconvolution/utils_time_series.py
scripts/test_deconvolution/archive/deconvolve_mocks.py
starred/__init__.py
starred/deconvolution/__init__.py
starred/deconvolution/deconvolution.py
starred/deconvolution/loss.py
starred/deconvolution/parameters.py
starred/optim/__init__.py
starred/optim/inference_base.py
starred/optim/optimization.py
starred/optim/sampling.py
starred/plots/__init__.py
starred/plots/f2n.py
starred/plots/plot_function.py
starred/procedures/__init__.py
starred/procedures/deconvolution_routines.py
starred/procedures/psf_routines.py
starred/psf/__init__.py
starred/psf/loss.py
starred/psf/parameters.py
starred/psf/psf.py
starred/utils/__init__.py
starred/utils/ds9reg.py
starred/utils/generic_utils.py
starred/utils/jax_utils.py
starred/utils/jax_utils_legacy.py
starred/utils/light_profile_analytical.py
starred/utils/noise_utils.py
starred/utils/parameters.py
starred_astro-1.4.8.dist-info/licenses/AUTHORS.md
starred_astro-1.4.8.dist-info/licenses/LICENSE
tests/__init__.py
tests/test_deconv/__init__.py
tests/test_deconv/test_deconv.py
tests/test_deconv/test_deconv_sersic.py
tests/test_plots/__init__.py
tests/test_plots/test_plots.py
tests/test_psf/__init__.py
tests/test_psf/test_convolution.py
tests/test_psf/test_distortion.py
tests/test_psf/test_psf.py
tests/test_psf/test_sanitize_inputs_psf.py
tests/test_utils/__init__.py
starred_astro-1.4.8.dist-info/METADATA
starred_astro-1.4.8.dist-info/WHEEL
starred_astro-1.4.8.dist-info/top_level.txt
starred_astro-1.4.8.dist-info/RECORD
