Metadata-Version: 2.4
Name: starred-astro
Version: 1.4.8
Summary: A two-channel deconvolution method with Starlet regularization
Author: Frédéric Dux
Author-email: Kevin Michalewicz <kevinmicha@hotmail.com>, Martin Millon <martin.millon@hotmail.fr>
License:                     GNU GENERAL PUBLIC LICENSE
Project-URL: homepage, https://cosmograil.gitlab.io/starred/index.html
Project-URL: repository, https://gitlab.com/cosmograil/starred
Keywords: deconvolution,astronomy,starlet,image processing
Classifier: Intended Audience :: Science/Research
Classifier: License :: OSI Approved :: GNU General Public License v3 (GPLv3)
Classifier: Programming Language :: Python :: 3
Classifier: Programming Language :: Python :: 3.8
Classifier: Topic :: Scientific/Engineering :: Astronomy
License-File: LICENSE
License-File: AUTHORS.md
Requires-Dist: astropy>=5.0.4
Requires-Dist: dill>=0.3.5.1
Requires-Dist: jax>=0.4.20
Requires-Dist: jaxlib>=0.4.20
Requires-Dist: matplotlib>=3.4.2
Requires-Dist: numpy>=1.21.2
Requires-Dist: scipy>=1.7.1
Requires-Dist: optax>=0.2.2
Requires-Dist: jaxopt>=0.8.3
Requires-Dist: tqdm>=4.64.0
Requires-Dist: h5py>=3.11.0
Provides-Extra: opt
Requires-Dist: emcee; extra == "opt"
Requires-Dist: mclmc; extra == "opt"
Requires-Dist: pyregion>=2.3.0; extra == "opt"
Requires-Dist: scikit-image; extra == "opt"
Provides-Extra: test
Requires-Dist: pytest; extra == "test"
Requires-Dist: pytest-cov; extra == "test"
Dynamic: license-file
